ds_logger/__init__.py
ds_logger/logger.py
ds_utils-0.4.1.dist-info/DESCRIPTION.rst
ds_utils-0.4.1.dist-info/METADATA
ds_utils-0.4.1.dist-info/RECORD
ds_utils-0.4.1.dist-info/WHEEL
ds_utils-0.4.1.dist-info/metadata.json
ds_utils-0.4.1.dist-info/top_level.txt
