Metadata-Version: 2.0
Name: ds-utils
Version: 0.4.1
Summary: Utilities for Hudl Data Science
Home-page: http://hudl.github.io/
Author: Nathan DeMaria
Author-email: nathan.demaria@hudl.com
License: MIT
Platform: UNKNOWN
Requires-Dist: boto
